alkymi/__init__.py
alkymi/checksums.py
alkymi/config.py
alkymi/core.py
alkymi/decorators.py
alkymi/foreach_recipe.py
alkymi/lab.py
alkymi/logging.py
alkymi/progress.py
alkymi/py.typed
alkymi/recipe.py
alkymi/recipes.py
alkymi/serialization.py
alkymi/types.py
alkymi/utils.py
alkymi/version.py
alkymi-0.3.1.dist-info/LICENSE.md
alkymi-0.3.1.dist-info/METADATA
alkymi-0.3.1.dist-info/WHEEL
alkymi-0.3.1.dist-info/top_level.txt
alkymi-0.3.1.dist-info/RECORD
