Metadata-Version: 2.1
Name: alkymi
Version: 0.3.1
Summary: alkymi - Pythonic task automation
Home-page: https://github.com/MathiasStokholm/alkymi
Author: =?utf-8?q?Mathias_B=C3=B8gh_Stokholm?=
Author-email: mathias.stokholm@gmail.com
License: MIT
Project-URL: Source, https://github.com/MathiasStokholm/alkymi/
Project-URL: Tracker, https://github.com/MathiasStokholm/alkymi/issues
Project-URL: Documentation, https://alkymi.readthedocs.io/en/latest/
Keywords: automation,pipeline,validation,preprocessing,make,build,task
Platform: UNKNOWN
Classifier: Development Status :: 4 - Beta
Classifier: License :: OSI Approved :: MIT License
Classifier: Environment :: Console
Classifier: Natural Language :: English
Classifier: Operating System :: OS Independent
Classifier: Programming Language :: Python :: 3
Classifier: Programming Language :: Python :: 3.7
Classifier: Programming Language :: Python :: 3.8
Classifier: Programming Language :: Python :: 3.9
Classifier: Programming Language :: Python :: 3.10
Classifier: Programming Language :: Python :: 3.11
Classifier: Intended Audience :: Developers
Classifier: Intended Audience :: Information Technology
Classifier: Intended Audience :: Science/Research
Classifier: Intended Audience :: System Administrators
Classifier: Topic :: Software Development :: Build Tools
Classifier: Topic :: Software Development :: Testing
Classifier: Topic :: Software Development :: Quality Assurance
Classifier: Topic :: Scientific/Engineering
Requires-Python: >=3.7
License-File: LICENSE.md
Requires-Dist: networkx (>=2.0)
Requires-Dist: rich (>=10.7)
Provides-Extra: xxhash
Requires-Dist: xxhash (>=2.0.0) ; extra == 'xxhash'
